{
  "parent": "minecraft:recipes/root",
  "rewards": {
    "recipes": [
	  "mcwfencesbyg:fir_picket_fence",
	  "mcwfencesbyg:fir_stockade_fence",
	  "mcwfencesbyg:fir_horse_fence",
	  "mcwfencesbyg:fir_wired_fence",
	  "mcwfencesbyg:fir_highley_gate",
	  "mcwfencesbyg:fir_pyramid_gate"
    ]
  },
  "criteria": {
    "has_acacia": {
      "trigger": "minecraft:inventory_changed",
      "conditions": {
        "items": [
          {
            "item": "biomeswevegone:fir_log"
          }
        ]
      }
    }
  },
  "requirements": [
    [
      "has_acacia"
    ]
  ]
}
